llm_trainer/__init__.py
llm_trainer/base_trainer.py
llm_trainer/checkpoint.py
llm_trainer/dataset.py
llm_trainer/dpo_trainer.py
llm_trainer/ds_checkpoint.py
llm_trainer/eval.py
llm_trainer/generate_utils.py
llm_trainer/grpo_trainer.py
llm_trainer/log.py
llm_trainer/loss.py
llm_trainer/parallel.py
llm_trainer/partition_utils.py
llm_trainer/ppo_trainer.py
llm_trainer/scheduler.py
llm_trainer/sft_trainer.py
llm_trainer/tokenizer.py
llm_trainer/tools.py
llm_trainer/train_configs.py
llm_trainer/trainer.py
llm_trainer/utils.py
project_llm_trainer-0.13.0.data/scripts/calc_intermediate_size
project_llm_trainer-0.13.0.data/scripts/ddp_train
project_llm_trainer-0.13.0.data/scripts/ds_train
project_llm_trainer-0.13.0.data/scripts/py_train
project_llm_trainer-0.13.0.data/scripts/smart_train
project_llm_trainer-0.13.0.data/scripts/vis_log
project_llm_trainer-0.13.0.data/scripts/vis_lr
project_llm_trainer-0.13.0.dist-info/METADATA
project_llm_trainer-0.13.0.dist-info/WHEEL
project_llm_trainer-0.13.0.dist-info/top_level.txt
project_llm_trainer-0.13.0.dist-info/RECORD
