Metadata-Version: 2.4
Name: project_llm_trainer
Version: 0.13.0
Summary: LLM and VLM trainer
Author: qibin
Author-email: qibin0506@gmail.com
Dynamic: author
Dynamic: author-email
Dynamic: summary
